dubo/__init__.py
dubo/api_client/__init__.py
dubo/api_client/api/__init__.py
dubo/api_client/api/dubo/__init__.py
dubo/api_client/api/dubo/read_query_v1_dubo_query_get.py
dubo/api_client/api/enterprise/__init__.py
dubo/api_client/api/enterprise/ask_dispatch_api_v1_dubo_query_generate_post.py
dubo/api_client/api/enterprise/ask_poll_api_v1_dubo_query_retrieve_get.py
dubo/api_client/api/enterprise/create_documentation_api_v1_dubo_documentation_post.py
dubo/api_client/api/enterprise/delete_document_by_id_api_v1_dubo_documentation_delete.py
dubo/api_client/api/enterprise/filter_documentation_endpoint_api_v1_dubo_query_filter_documentation_get.py
dubo/api_client/api/enterprise/read_all_api_v1_dubo_documentation_get.py
dubo/api_client/api/enterprise/read_one_api_v1_dubo_documentation_data_source_documentation_id_get.py
dubo/api_client/api/enterprise/update_document_api_v1_dubo_documentation_put.py
dubo/api_client/api/sdk/__init__.py
dubo/api_client/api/sdk/create_dubo_chart_v1_dubo_chart_post.py
dubo/api_client/api/sdk/get_query_execution_category_v1_dubo_categorize_chart_get.py
dubo/api_client/client.py
dubo/api_client/errors.py
dubo/api_client/models/__init__.py
dubo/api_client/models/ask_dispatch_response.py
dubo/api_client/models/ask_dispatch_response_results_set_item.py
dubo/api_client/models/attenuated_ddl.py
dubo/api_client/models/body_create_documentation_api_v1_dubo_documentation_post.py
dubo/api_client/models/body_read_query_v1_dubo_query_get.py
dubo/api_client/models/body_update_document_api_v1_dubo_documentation_put.py
dubo/api_client/models/chart_type.py
dubo/api_client/models/create_api_query.py
dubo/api_client/models/create_api_query_mode.py
dubo/api_client/models/data_source_document.py
dubo/api_client/models/dubo_chart_query.py
dubo/api_client/models/dubo_chart_query_chart_spec.py
dubo/api_client/models/dubo_chart_query_data_snippet_item.py
dubo/api_client/models/dubo_example.py
dubo/api_client/models/http_validation_error.py
dubo-0.2.13.dist-info/LICENSE
dubo-0.2.13.dist-info/WHEEL
dubo-0.2.13.dist-info/METADATA
dubo-0.2.13.dist-info/RECORD
